{
	"type": "ItemTurret",
	"name": "Spider",
	"description": "An prototype of an expandable turret name is placeholder.",
	"health": 220,
	"size": 2,
	"range": 160,
	"shootEffect": "none",
	"smokeEffect": "none",
	"reloadTime": 60,
	"shots": 4,
	"burstSpacing": 2,
	"ammoTypes": {
		"notrite": {
			"type": "MissileBulletType",
			"damage": 50,
			"speed": 4,
			"lifetime": 40
		},
		"magnetite": {
			"type": "MissileBulletType",
			"damage": 75,
			"speed": 5,
			"lifetime": 32
		}
	},
	"requirements": [
		{"item": "magnetite", "amount": 50},
		{"item": "notrite", "amount": 35},
		{"item": "dense-alloy", "amount": 85},
		{"item": "silicon", "amount": 125},
	],
	"category": "turret",
	"buildVisibility": "shown",
	"research": "b-brainstorm"
}